README
elo.py
setup.py
elo.egg-info/PKG-INFO
elo.egg-info/SOURCES.txt
elo.egg-info/dependency_links.txt
elo.egg-info/requires.txt
elo.egg-info/top_level.txt